llm_logging_debug.py
llm_logging_debug-0.1.dist-info/licenses/LICENSE
llm_logging_debug-0.1.dist-info/METADATA
llm_logging_debug-0.1.dist-info/WHEEL
llm_logging_debug-0.1.dist-info/entry_points.txt
llm_logging_debug-0.1.dist-info/top_level.txt
llm_logging_debug-0.1.dist-info/RECORD
