Metadata-Version: 2.4
Name: llm-logging-debug
Version: 0.1
Summary: Set logging.DEBUG while running LLM
Author: Simon Willison
License-Expression: Apache-2.0
Project-URL: Homepage, https://github.com/simonw/llm-logging-debug
Project-URL: Changelog, https://github.com/simonw/llm-logging-debug/releases
Project-URL: Issues, https://github.com/simonw/llm-logging-debug/issues
Project-URL: CI, https://github.com/simonw/llm-logging-debug/actions
Requires-Python: >=3.9
License-File: LICENSE
Requires-Dist: llm
Provides-Extra: test
Requires-Dist: pytest; extra == "test"
Dynamic: license-file
